drf_turnstile/__init__.py
drf_turnstile/apps.py
drf_turnstile/checks.py
drf_turnstile/client.py
drf_turnstile/constants.py
drf_turnstile/fields.py
drf_turnstile/validators.py
drf_turnstile-0.0.1.dist-info/METADATA
drf_turnstile-0.0.1.dist-info/WHEEL
drf_turnstile-0.0.1.dist-info/top_level.txt
drf_turnstile-0.0.1.dist-info/RECORD
